{"sso.fed.prod.aws.swalife.com": {"history": [{"name": "sso.prod0.fed.prod.aws.swalife.com", "ip_address": "3.219.11.91", "resolve_time": 0.047298, "timestamp": "2025-02-02 17:45:03", "hanger": "hanger0"}, {"name": "sso.prod0.fed.prod.aws.swalife.com", "ip_address": "3.219.11.91", "resolve_time": 0.043097, "timestamp": "2025-02-02 18:45:41", "hanger": "hanger0"}], "last_ip_change": "2025-02-02 17:45:03"}, "sso.fed.prod.aws.swacorp.com": {"history": [{"name": "DNS Failed", "ip_address": "", "resolve_time": 0.143792, "timestamp": "2025-02-02 17:45:03", "hanger": "Unknown"}, {"name": "DNS Failed", "ip_address": "", "resolve_time": 0.126452, "timestamp": "2025-02-02 18:45:41", "hanger": "Unknown"}]}, "sso.cfi.prod.aws.southwest.com": {"history": [{"name": "sso.prod0.cfi.prod.aws.southwest.com", "ip_address": "34.216.136.55", "resolve_time": 0.142706, "timestamp": "2025-02-02 17:45:03", "hanger": "hanger0"}, {"name": "sso.prod0.cfi.prod.aws.southwest.com", "ip_address": "34.216.136.55", "resolve_time": 0.149774, "timestamp": "2025-02-02 18:45:41", "hanger": "hanger0"}], "last_ip_change": "2025-02-02 17:45:03"}, "sso.fed.qa.aws.swacorp.com": {"history": [{"name": "DNS Failed", "ip_address": "", "resolve_time": 0.138629, "timestamp": "2025-02-02 17:45:03", "hanger": "Unknown"}, {"name": "DNS Failed", "ip_address": "", "resolve_time": 0.125052, "timestamp": "2025-02-02 18:45:41", "hanger": "Unknown"}]}, "sso.fed.qa.aws.swalife.com": {"history": [{"name": "sso.qa1.fed.qa.aws.swalife.com", "ip_address": "34.194.221.188", "resolve_time": 0.100545, "timestamp": "2025-02-02 17:45:03", "hanger": "hanger1"}, {"name": "sso.qa1.fed.qa.aws.swalife.com", "ip_address": "34.194.221.188", "resolve_time": 0.141084, "timestamp": "2025-02-02 18:45:41", "hanger": "hanger1"}], "last_ip_change": "2025-02-02 17:45:03"}, "sso.fed.dev.aws.swalife.com": {"history": [{"name": "sso.dev1.fed.dev.aws.swalife.com", "ip_address": "23.22.96.242", "resolve_time": 0.137143, "timestamp": "2025-02-02 17:45:03", "hanger": "hanger1"}, {"name": "sso.dev1.fed.dev.aws.swalife.com", "ip_address": "34.236.54.42", "resolve_time": 0.129258, "timestamp": "2025-02-02 18:45:41", "hanger": "hanger1"}], "last_ip_change": "2025-02-02 18:45:41"}, "sso.fed.dev.aws.swacorp.com": {"history": [{"name": "DNS Failed", "ip_address": "", "resolve_time": 0.094575, "timestamp": "2025-02-02 17:45:03", "hanger": "Unknown"}, {"name": "DNS Failed", "ip_address": "", "resolve_time": 0.129048, "timestamp": "2025-02-02 18:45:41", "hanger": "Unknown"}]}}